{
    "readings": {
        "reading-1": {
            "lang": [
                {
                    "passage": "Exodus 2:11-22"
                },
                {
                    "passage": "╔xodo 2:11-22"
                }
            ],
            "tag": "am"
        },
        "ls-1": {
            "reading": 93,
            "background": "supper-chalice"
        },
        "sermon-1": {
            "title": "Glimpses of Eternity",
            "tĒtulo": "Destellos de la eternidad"
        }
    }
}